{"config":{"payjswx":{"id":"1","payment":"PAYJS(\u5fae\u4fe1)","payname":"\u5fae\u4fe1","payimage":"\/res\/images\/pay\/weixin.jpg","alias":"payjswx","sign_type":"MD5","app_id":"1508289451","app_secret":"yOCCIeuEdxfeEsgD","ali_public_key":null,"rsa_private_key":null,"configure3":"","configure4":"","overtime":"0","active":"1"},"payjsalipay":{"id":"2","payment":"PAYJS(\u652f\u4ed8\u5b9d)","payname":"\u652f\u4ed8\u5b9d","payimage":"\/res\/images\/pay\/alipay.jpg","alias":"payjsalipay","sign_type":"MD5","app_id":"1523943811","app_secret":"XXwXsf93tvst9LI1","ali_public_key":null,"rsa_private_key":null,"configure3":"","configure4":"","overtime":"0","active":"1"}},"expire_time":1559461532}